siqa_hash/__init__.py
siqa_hash/siqa_hashcode.py
siqa_hash-0.2.0.dist-info/LICENSE
siqa_hash-0.2.0.dist-info/METADATA
siqa_hash-0.2.0.dist-info/WHEEL
siqa_hash-0.2.0.dist-info/entry_points.txt
siqa_hash-0.2.0.dist-info/top_level.txt
siqa_hash-0.2.0.dist-info/RECORD
