Metadata-Version: 2.1
Name: siqa_hash
Version: 0.2.0
Summary: Quantum hash function built using Qiskit
Home-page: https://github.com/MohanaPriyaThineshKumar/SIQA_Hash
Author: Mohana Priya Thinesh Kumar
Author-email: manthramohana1@gmail.com
License: MIT
Requires-Python: >=3.8
License-File: LICENSE
Requires-Dist: qiskit>=1.0.0
Requires-Dist: qiskit-aer
Requires-Dist: numpy
